[
  {
    "ContainingType": "EmployeeShiftSystem.Controllers.EmployeesController",
    "Method": "AddEmployee",
    "RelativePath": "api/employees",
    "HttpMethod": "POST",
    "IsController": true,
    "Order": 0,
    "Parameters": [
      {
        "Name": "employee",
        "Type": "EmployeeShiftSystem.Models.Employee",
        "IsRequired": true
      }
    ],
    "ReturnTypes": []
  },
  {
    "ContainingType": "EmployeeShiftSystem.Controllers.EmployeesController",
    "Method": "GetEmployees",
    "RelativePath": "api/employees",
    "HttpMethod": "GET",
    "IsController": true,
    "Order": 0,
    "Parameters": [],
    "ReturnTypes": []
  },
  {
    "ContainingType": "EmployeeShiftSystem.Controllers.LeaveController",
    "Method": "RequestLeave",
    "RelativePath": "api/leave",
    "HttpMethod": "POST",
    "IsController": true,
    "Order": 0,
    "Parameters": [
      {
        "Name": "request",
        "Type": "EmployeeShiftSystem.Models.LeaveRequest",
        "IsRequired": true
      }
    ],
    "ReturnTypes": []
  },
  {
    "ContainingType": "EmployeeShiftSystem.Controllers.LeaveController",
    "Method": "ApproveLeave",
    "RelativePath": "api/leave/{id}/approve",
    "HttpMethod": "PUT",
    "IsController": true,
    "Order": 0,
    "Parameters": [
      {
        "Name": "id",
        "Type": "System.Int32",
        "IsRequired": true
      }
    ],
    "ReturnTypes": []
  },
  {
    "ContainingType": "EmployeeShiftSystem.Controllers.ShiftsController",
    "Method": "CreateShift",
    "RelativePath": "api/shifts",
    "HttpMethod": "POST",
    "IsController": true,
    "Order": 0,
    "Parameters": [
      {
        "Name": "shift",
        "Type": "EmployeeShiftSystem.Models.Shift",
        "IsRequired": true
      }
    ],
    "ReturnTypes": []
  },
  {
    "ContainingType": "EmployeeShiftSystem.Controllers.ShiftsController",
    "Method": "GetShifts",
    "RelativePath": "api/shifts",
    "HttpMethod": "GET",
    "IsController": true,
    "Order": 0,
    "Parameters": [],
    "ReturnTypes": []
  }
]